[{"color":"#ff0a0a","id":1,"icon":"bezier.svg","points":[{"id":0,"x":142,"y":413},{"id":1,"x":321,"y":561},{"id":2,"x":951,"y":587},{"id":3,"x":887,"y":374}],"name":"Bezier1","userId":1,"width":"5","fill":false},{"color":"#ff0a0a","id":2,"icon":"rect.svg","points":[{"id":0,"x":209,"y":126},{"id":1,"x":368,"y":285}],"name":"rectangle1","userId":1,"width":"5","fill":false},{"color":"#ff0a0a","id":3,"icon":"rect.svg","points":[{"id":0,"x":513,"y":94},{"id":1,"x":790,"y":331}],"name":"rectangle2","userId":1,"width":"5","fill":false},{"color":"#ff0a0a","id":4,"icon":"line.svg","points":[{"id":0,"x":241,"y":160},{"id":1,"x":336,"y":257}],"name":"line1","userId":1,"width":"5","distance":135.77186748365804},{"color":"#ff0a0a","id":5,"icon":"line.svg","points":[{"id":0,"x":258,"y":260},{"id":1,"x":329,"y":162}],"name":"line2","userId":1,"width":"5","distance":121.01652779682617},{"color":"#ff0a0a","id":6,"icon":"line.svg","points":[{"id":0,"x":561,"y":132},{"id":1,"x":755,"y":298}],"name":"line3","userId":1,"width":"5","distance":255.32724100651697},{"color":"#ff0a0a","id":7,"icon":"line.svg","points":[{"id":0,"x":584,"y":295},{"id":1,"x":732,"y":127}],"name":"line4","userId":1,"width":"5","distance":223.89283150650448},{"color":"#ff0a0a","id":8,"icon":"brush.svg","points":[{"id":0,"x":679,"y":589},{"id":1,"x":679,"y":590},{"id":2,"x":679,"y":591},{"id":3,"x":679,"y":594},{"id":4,"x":678,"y":598},{"id":5,"x":677,"y":603},{"id":6,"x":676,"y":609},{"id":7,"x":672,"y":613},{"id":8,"x":671,"y":618},{"id":9,"x":669,"y":622},{"id":10,"x":667,"y":627},{"id":11,"x":665,"y":631},{"id":12,"x":665,"y":633},{"id":13,"x":663,"y":636},{"id":14,"x":663,"y":637},{"id":15,"x":662,"y":638},{"id":16,"x":662,"y":640},{"id":17,"x":662,"y":640}],"name":"brush1","userId":1,"width":"5"},{"color":"#ff0a0a","id":9,"icon":"brush.svg","points":[{"id":0,"x":678,"y":585},{"id":1,"x":679,"y":585},{"id":2,"x":680,"y":585},{"id":3,"x":681,"y":585},{"id":4,"x":682,"y":586},{"id":5,"x":684,"y":588},{"id":6,"x":685,"y":590},{"id":7,"x":687,"y":594},{"id":8,"x":688,"y":599},{"id":9,"x":690,"y":604},{"id":10,"x":691,"y":608},{"id":11,"x":693,"y":612},{"id":12,"x":695,"y":617},{"id":13,"x":696,"y":621},{"id":14,"x":697,"y":624},{"id":15,"x":698,"y":627},{"id":16,"x":699,"y":628},{"id":17,"x":700,"y":630},{"id":18,"x":701,"y":631},{"id":19,"x":701,"y":632},{"id":20,"x":701,"y":632}],"name":"brush2","userId":1,"width":"5"},{"color":"#ff0a0a","id":10,"icon":"brush.svg","points":[{"id":0,"x":673,"y":620},{"id":1,"x":674,"y":620},{"id":2,"x":675,"y":620},{"id":3,"x":676,"y":620},{"id":4,"x":677,"y":620},{"id":5,"x":678,"y":620},{"id":6,"x":679,"y":620},{"id":7,"x":681,"y":620},{"id":8,"x":683,"y":620},{"id":9,"x":685,"y":620},{"id":10,"x":686,"y":620},{"id":11,"x":687,"y":620},{"id":12,"x":688,"y":620},{"id":13,"x":689,"y":620},{"id":14,"x":689,"y":620}],"name":"brush3","userId":1,"width":"5"},{"color":"#ff0a0a","id":11,"icon":"brush.svg","points":[{"id":0,"x":716,"y":589},{"id":1,"x":716,"y":588},{"id":2,"x":716,"y":587},{"id":3,"x":718,"y":587},{"id":4,"x":722,"y":585},{"id":5,"x":724,"y":585},{"id":6,"x":726,"y":584},{"id":7,"x":729,"y":584},{"id":8,"x":730,"y":584},{"id":9,"x":731,"y":584},{"id":10,"x":732,"y":584},{"id":11,"x":733,"y":585},{"id":12,"x":735,"y":586},{"id":13,"x":736,"y":588},{"id":14,"x":737,"y":591},{"id":15,"x":738,"y":592},{"id":16,"x":738,"y":595},{"id":17,"x":740,"y":597},{"id":18,"x":740,"y":600},{"id":19,"x":740,"y":601},{"id":20,"x":740,"y":603},{"id":21,"x":740,"y":604},{"id":22,"x":740,"y":605},{"id":23,"x":739,"y":605},{"id":24,"x":738,"y":605},{"id":25,"x":737,"y":605},{"id":26,"x":737,"y":606},{"id":27,"x":737,"y":607},{"id":28,"x":735,"y":607},{"id":29,"x":734,"y":607},{"id":30,"x":734,"y":608},{"id":31,"x":733,"y":608},{"id":32,"x":734,"y":608},{"id":33,"x":736,"y":609},{"id":34,"x":738,"y":610},{"id":35,"x":740,"y":611},{"id":36,"x":742,"y":613},{"id":37,"x":745,"y":613},{"id":38,"x":746,"y":615},{"id":39,"x":747,"y":616},{"id":40,"x":749,"y":617},{"id":41,"x":750,"y":619},{"id":42,"x":751,"y":619},{"id":43,"x":753,"y":620},{"id":44,"x":753,"y":621},{"id":45,"x":754,"y":621},{"id":46,"x":755,"y":621},{"id":47,"x":755,"y":622},{"id":48,"x":755,"y":623},{"id":49,"x":754,"y":623},{"id":50,"x":754,"y":624},{"id":51,"x":753,"y":625},{"id":52,"x":752,"y":625},{"id":53,"x":751,"y":626},{"id":54,"x":750,"y":627},{"id":55,"x":748,"y":628},{"id":56,"x":747,"y":629},{"id":57,"x":746,"y":629},{"id":58,"x":745,"y":630},{"id":59,"x":743,"y":632},{"id":60,"x":741,"y":633},{"id":61,"x":739,"y":633},{"id":62,"x":738,"y":634},{"id":63,"x":736,"y":636},{"id":64,"x":734,"y":636},{"id":65,"x":733,"y":637},{"id":66,"x":732,"y":637},{"id":67,"x":731,"y":637},{"id":68,"x":730,"y":637},{"id":69,"x":730,"y":637}],"name":"brush4","userId":1,"width":"5"},{"color":"#ff0a0a","id":12,"icon":"brush.svg","points":[{"id":0,"x":771,"y":583},{"id":1,"x":772,"y":583},{"id":2,"x":773,"y":584},{"id":3,"x":773,"y":585},{"id":4,"x":773,"y":586},{"id":5,"x":774,"y":588},{"id":6,"x":774,"y":590},{"id":7,"x":774,"y":593},{"id":8,"x":774,"y":596},{"id":9,"x":774,"y":600},{"id":10,"x":774,"y":604},{"id":11,"x":774,"y":609},{"id":12,"x":774,"y":613},{"id":13,"x":774,"y":618},{"id":14,"x":774,"y":622},{"id":15,"x":774,"y":626},{"id":16,"x":774,"y":629},{"id":17,"x":774,"y":631},{"id":18,"x":774,"y":634},{"id":19,"x":774,"y":635},{"id":20,"x":775,"y":635},{"id":21,"x":775,"y":635}],"name":"brush5","userId":1,"width":"5"},{"color":"#ff0a0a","id":13,"icon":"brush.svg","points":[{"id":0,"x":771,"y":582},{"id":1,"x":772,"y":582},{"id":2,"x":773,"y":582},{"id":3,"x":774,"y":582},{"id":4,"x":775,"y":582},{"id":5,"x":778,"y":584},{"id":6,"x":781,"y":588},{"id":7,"x":784,"y":591},{"id":8,"x":787,"y":596},{"id":9,"x":789,"y":601},{"id":10,"x":791,"y":605},{"id":11,"x":793,"y":610},{"id":12,"x":794,"y":614},{"id":13,"x":795,"y":618},{"id":14,"x":795,"y":622},{"id":15,"x":797,"y":625},{"id":16,"x":797,"y":628},{"id":17,"x":798,"y":630},{"id":18,"x":798,"y":633},{"id":19,"x":799,"y":634},{"id":20,"x":801,"y":637},{"id":21,"x":802,"y":640},{"id":22,"x":803,"y":641},{"id":23,"x":804,"y":643},{"id":24,"x":805,"y":644},{"id":25,"x":805,"y":646},{"id":26,"x":806,"y":646},{"id":27,"x":806,"y":646}],"name":"brush6","userId":1,"width":"5"},{"color":"#ff0a0a","id":14,"icon":"brush.svg","points":[{"id":0,"x":771,"y":619},{"id":1,"x":771,"y":618},{"id":2,"x":772,"y":618},{"id":3,"x":773,"y":618},{"id":4,"x":774,"y":618},{"id":5,"x":775,"y":618},{"id":6,"x":777,"y":618},{"id":7,"x":778,"y":618},{"id":8,"x":780,"y":618},{"id":9,"x":781,"y":618},{"id":10,"x":781,"y":618}],"name":"brush7","userId":1,"width":"5"},{"color":"#ff0a0a","id":15,"icon":"brush.svg","points":[{"id":0,"x":848,"y":577},{"id":1,"x":849,"y":577},{"id":2,"x":855,"y":578},{"id":3,"x":856,"y":579},{"id":4,"x":859,"y":580},{"id":5,"x":862,"y":582},{"id":6,"x":864,"y":583},{"id":7,"x":866,"y":584},{"id":8,"x":868,"y":586},{"id":9,"x":870,"y":588},{"id":10,"x":870,"y":590},{"id":11,"x":871,"y":592},{"id":12,"x":871,"y":593},{"id":13,"x":871,"y":596},{"id":14,"x":871,"y":598},{"id":15,"x":871,"y":600},{"id":16,"x":871,"y":602},{"id":17,"x":869,"y":604},{"id":18,"x":867,"y":606},{"id":19,"x":865,"y":607},{"id":20,"x":864,"y":607},{"id":21,"x":863,"y":608},{"id":22,"x":862,"y":608},{"id":23,"x":861,"y":609},{"id":24,"x":860,"y":609},{"id":25,"x":860,"y":610},{"id":26,"x":861,"y":610},{"id":27,"x":862,"y":611},{"id":28,"x":863,"y":611},{"id":29,"x":865,"y":611},{"id":30,"x":866,"y":613},{"id":31,"x":868,"y":613},{"id":32,"x":870,"y":615},{"id":33,"x":871,"y":615},{"id":34,"x":874,"y":616},{"id":35,"x":875,"y":617},{"id":36,"x":876,"y":619},{"id":37,"x":877,"y":620},{"id":38,"x":879,"y":621},{"id":39,"x":879,"y":623},{"id":40,"x":879,"y":624},{"id":41,"x":879,"y":625},{"id":42,"x":880,"y":625},{"id":43,"x":880,"y":626},{"id":44,"x":880,"y":627},{"id":45,"x":881,"y":629},{"id":46,"x":881,"y":631},{"id":47,"x":881,"y":633},{"id":48,"x":881,"y":635},{"id":49,"x":881,"y":636},{"id":50,"x":881,"y":637},{"id":51,"x":881,"y":638},{"id":52,"x":881,"y":639},{"id":53,"x":881,"y":640},{"id":54,"x":880,"y":641},{"id":55,"x":880,"y":642},{"id":56,"x":878,"y":642},{"id":57,"x":877,"y":643},{"id":58,"x":875,"y":644},{"id":59,"x":874,"y":644},{"id":60,"x":872,"y":644},{"id":61,"x":870,"y":645},{"id":62,"x":867,"y":645},{"id":63,"x":864,"y":645},{"id":64,"x":862,"y":645},{"id":65,"x":860,"y":645},{"id":66,"x":859,"y":645},{"id":67,"x":859,"y":645}],"name":"brush8","userId":1,"width":"5"},{"color":"#ff0a0a","id":16,"icon":"brush.svg","points":[{"id":0,"x":902,"y":581},{"id":1,"x":903,"y":581},{"id":2,"x":904,"y":582},{"id":3,"x":904,"y":584},{"id":4,"x":905,"y":588},{"id":5,"x":906,"y":594},{"id":6,"x":907,"y":599},{"id":7,"x":907,"y":604},{"id":8,"x":907,"y":611},{"id":9,"x":907,"y":618},{"id":10,"x":907,"y":623},{"id":11,"x":905,"y":629},{"id":12,"x":905,"y":634},{"id":13,"x":905,"y":639},{"id":14,"x":905,"y":644},{"id":15,"x":904,"y":648},{"id":16,"x":904,"y":651},{"id":17,"x":904,"y":652},{"id":18,"x":904,"y":653},{"id":19,"x":904,"y":654},{"id":20,"x":904,"y":654}],"name":"brush9","userId":1,"width":"5"},{"color":"#ff0a0a","id":17,"icon":"brush.svg","points":[{"id":0,"x":904,"y":586},{"id":1,"x":905,"y":586},{"id":2,"x":906,"y":586},{"id":3,"x":908,"y":588},{"id":4,"x":911,"y":590},{"id":5,"x":914,"y":594},{"id":6,"x":917,"y":599},{"id":7,"x":920,"y":604},{"id":8,"x":922,"y":608},{"id":9,"x":925,"y":613},{"id":10,"x":927,"y":618},{"id":11,"x":930,"y":622},{"id":12,"x":932,"y":627},{"id":13,"x":934,"y":630},{"id":14,"x":935,"y":633},{"id":15,"x":937,"y":637},{"id":16,"x":938,"y":639},{"id":17,"x":939,"y":641},{"id":18,"x":940,"y":644},{"id":19,"x":940,"y":645},{"id":20,"x":941,"y":645},{"id":21,"x":941,"y":645}],"name":"brush10","userId":1,"width":"5"},{"color":"#ff0a0a","id":18,"icon":"brush.svg","points":[{"id":0,"x":908,"y":626},{"id":1,"x":909,"y":626},{"id":2,"x":910,"y":626},{"id":3,"x":911,"y":626},{"id":4,"x":914,"y":627},{"id":5,"x":915,"y":627},{"id":6,"x":918,"y":627},{"id":7,"x":919,"y":627},{"id":8,"x":921,"y":627},{"id":9,"x":923,"y":627},{"id":10,"x":924,"y":627},{"id":11,"x":925,"y":627},{"id":12,"x":926,"y":627},{"id":13,"x":926,"y":627}],"name":"brush11","userId":1,"width":"5"},{"color":"#ff0000","id":20,"icon":"bezier.svg","points":[{"id":0,"x":784,"y":505},{"id":1,"x":847,"y":539},{"id":2,"x":1011,"y":512},{"id":3,"x":883,"y":440}],"name":"Bezier3","userId":1,"width":"4","fill":false}]