{"countClick":0,"brushWidth":1,"brushColor":"#00fa3e","fillStatus":true,"backgroundColor":"#FFFFFF","width":900,"height":500,"canvas":{},"ctx":{},"canvasAnimate":{"_vei":{}},"ctxAnimate":{},"users":[{"lastName":"Rukavchickov","firstName":"Alex","login":"LeshaHoroshiy","email":"123@mail.ru","password":"8bb0cf6eb9b17d0f7d22b456f121257dc1254e1f01665370476383ea776df414","avatar":"e198b8dbddace375ebf6d706ee39452820f933d5daae50b9f864ae9a98e07a69.jpg","status":false,"id":1,"socketId":"","color":"#000","cursor":{"x":0,"y":0}}],"state":3,"shapes":[{"color":"#0be519","id":100,"icon":"circle.svg","isVisible":true,"points":[{"id":0,"x":572,"y":201},{"id":1,"x":502,"y":156}],"name":"Circle33","userId":1,"width":1,"fill":true,"radius":83.21658488546619},{"color":"#fafafa","id":101,"icon":"circle.svg","isVisible":true,"points":[{"id":0,"x":529,"y":189},{"id":1,"x":516,"y":179}],"name":"Circle34","userId":1,"width":1,"fill":true,"radius":16.401219466856727},{"color":"#fafafa","id":102,"icon":"circle.svg","isVisible":true,"points":[{"id":0,"x":605,"y":195},{"id":1,"x":584,"y":180}],"name":"Circle35","userId":1,"width":1,"fill":true,"radius":25.80697580112788},{"color":"#fafafa","id":104,"icon":"bezier.svg","isVisible":true,"points":[{"id":0,"x":524,"y":239},{"id":1,"x":544,"y":260},{"id":2,"x":593,"y":266},{"id":3,"x":609,"y":246}],"name":"Bezier19","userId":1,"width":1,"fill":false},{"color":"#00fa3e","id":106,"icon":"rect.svg","isVisible":true,"points":[{"id":0,"x":441,"y":302},{"id":1,"x":708,"y":488}],"name":"rectangle22","userId":1,"width":1,"fill":true}],"shapesHistory":[{"color":"#0be519","id":100,"icon":"circle.svg","isVisible":true,"points":[{"id":0,"x":572,"y":201},{"id":1,"x":502,"y":156}],"name":"Circle33","userId":1,"width":1,"fill":true,"radius":83.21658488546619},{"color":"#fafafa","id":101,"icon":"circle.svg","isVisible":true,"points":[{"id":0,"x":529,"y":189},{"id":1,"x":516,"y":179}],"name":"Circle34","userId":1,"width":1,"fill":true,"radius":16.401219466856727},{"color":"#fafafa","id":102,"icon":"circle.svg","isVisible":true,"points":[{"id":0,"x":605,"y":195},{"id":1,"x":584,"y":180}],"name":"Circle35","userId":1,"width":1,"fill":true,"radius":25.80697580112788},{"color":"#fafafa","id":104,"icon":"bezier.svg","isVisible":true,"points":[{"id":0,"x":524,"y":239},{"id":1,"x":544,"y":260},{"id":2,"x":593,"y":266},{"id":3,"x":609,"y":246}],"name":"Bezier19","userId":1,"width":1,"fill":false},{"color":"#00fa3e","id":106,"icon":"rect.svg","isVisible":true,"points":[{"id":0,"x":441,"y":302},{"id":1,"x":708,"y":488}],"name":"rectangle22","userId":1,"width":1,"fill":true}],"currentShape":{"color":"#00fa3e","id":106,"icon":"rect.svg","isVisible":true,"points":[{"id":0,"x":441,"y":302},{"id":1,"x":708,"y":488}],"name":"rectangle22","userId":1,"width":1,"fill":true}}